URLRakshak-0.0.4.data/scripts/URLRakshak
fakeurldetector/API.py
fakeurldetector/BaseConfig.py
fakeurldetector/__init__.py
fakeurldetector/version.py
fakeurldetector/data/__init__.py
fakeurldetector/data/model.pkl
fakeurldetector/helpers/__init__.py
fakeurldetector/helpers/api_auth.py
fakeurldetector/helpers/database.py
fakeurldetector/helpers/get_ssl_certificate.py
fakeurldetector/helpers/models.py
fakeurldetector/helpers/selenium_redirected_url.py
fakeurldetector/helpers/url_helper.py
fakeurldetector/routers/__init__.py
fakeurldetector/routers/detection.py
fakeurldetector/routers/users.py
URLRakshak-0.0.4.dist-info/LICENSE
URLRakshak-0.0.4.dist-info/METADATA
URLRakshak-0.0.4.dist-info/WHEEL
URLRakshak-0.0.4.dist-info/top_level.txt
URLRakshak-0.0.4.dist-info/RECORD
